knowledge/__init__.py
knowledge/base/__init__.py
knowledge/base/access.py
knowledge/base/entity.py
knowledge/base/language.py
knowledge/base/ontology.py
knowledge/base/queue.py
knowledge/base/response.py
knowledge/base/search.py
knowledge/base/tenant.py
knowledge/nel/__init__.py
knowledge/nel/base.py
knowledge/nel/engine.py
knowledge/ontomapping/__init__.py
knowledge/ontomapping/manager.py
knowledge/public/__init__.py
knowledge/public/cache.py
knowledge/public/client.py
knowledge/public/helper.py
knowledge/public/relations.py
knowledge/public/wikidata.py
knowledge/services/__init__.py
knowledge/services/asyncio/__init__.py
knowledge/services/asyncio/base.py
knowledge/services/asyncio/graph.py
knowledge/services/asyncio/group.py
knowledge/services/asyncio/search.py
knowledge/services/asyncio/users.py
knowledge/services/base.py
knowledge/services/graph.py
knowledge/services/group.py
knowledge/services/helper.py
knowledge/services/ontology.py
knowledge/services/search.py
knowledge/services/session.py
knowledge/services/tenant.py
knowledge/services/users.py
knowledge/utils/__init__.py
knowledge/utils/diff.py
knowledge/utils/graph.py
knowledge/utils/import_format.py
knowledge/utils/wikidata.py
knowledge/utils/wikipedia.py
personal_knowledge_library-4.0.4.dist-info/METADATA
personal_knowledge_library-4.0.4.dist-info/WHEEL
personal_knowledge_library-4.0.4.dist-info/licenses/LICENSE
personal_knowledge_library-4.0.4.dist-info/RECORD
