Metadata-Version: 2.4
Name: personal_knowledge_library
Version: 4.0.4
Summary: Library to access Wacom's Personal Knowledge graph.
License-Expression: Apache-2.0
License-File: LICENSE
Keywords: semantic-knowledge,knowledge-graph
Author: Markus Weber
Author-email: markus.weber@wacom.com
Requires-Python: >=3.10,<4.0
Classifier: Topic :: Software Development :: Libraries :: Python Modules
Classifier: Programming Language :: Python :: 3
Classifier: Programming Language :: Python :: 3.9
Classifier: Programming Language :: Python :: 3.10
Classifier: Programming Language :: Python :: 3.11
Classifier: Programming Language :: Python :: 3.12
Classifier: Programming Language :: Python :: 3.13
Provides-Extra: dev
Requires-Dist: Faker (==18.9.0) ; extra == "dev"
Requires-Dist: PyJWT (==2.10.1)
Requires-Dist: aiohttp[speedups]
Requires-Dist: black (>=24.2.0) ; extra == "dev"
Requires-Dist: cachetools (>=5.3.0)
Requires-Dist: certifi
Requires-Dist: flake8 (>=6.0.0) ; extra == "dev"
Requires-Dist: loguru (==0.7.3)
Requires-Dist: mypy (>=1.8.0) ; extra == "dev"
Requires-Dist: ndjson (>=0.3.1)
Requires-Dist: orjson (>=3.10.0)
Requires-Dist: pdoc3 ; extra == "dev"
Requires-Dist: pylint (>=2.17.0) ; extra == "dev"
Requires-Dist: pytest ; extra == "dev"
Requires-Dist: pytest-asyncio ; extra == "dev"
Requires-Dist: pytest-cov ; extra == "dev"
Requires-Dist: pytest-env ; extra == "dev"
Requires-Dist: pytest-mock ; extra == "dev"
Requires-Dist: python-dateutil (>=2.8.2)
Requires-Dist: rdflib (>=7.1.0)
Requires-Dist: requests (>=2.32.0)
Requires-Dist: tox (>=4.0.0) ; extra == "dev"
Requires-Dist: tqdm (>=4.65.0)
